cdk_cloudformation_dynatrace_configuration_dashboard/__init__.py
cdk_cloudformation_dynatrace_configuration_dashboard/py.typed
cdk_cloudformation_dynatrace_configuration_dashboard/_jsii/__init__.py
cdk_cloudformation_dynatrace_configuration_dashboard/_jsii/dynatrace-configuration-dashboard@1.6.0-alpha.7.jsii.tgz
cdk_cloudformation_dynatrace_configuration_dashboard-1.6.0a7.dist-info/LICENSE
cdk_cloudformation_dynatrace_configuration_dashboard-1.6.0a7.dist-info/METADATA
cdk_cloudformation_dynatrace_configuration_dashboard-1.6.0a7.dist-info/WHEEL
cdk_cloudformation_dynatrace_configuration_dashboard-1.6.0a7.dist-info/top_level.txt
cdk_cloudformation_dynatrace_configuration_dashboard-1.6.0a7.dist-info/RECORD
